README.md
setup.cfg
setup.py
tabml/__init__.py
tabml/config_helpers.py
tabml/data_loaders.py
tabml/data_processing.py
tabml/datasets.py
tabml/experiment_manager.py
tabml/feature_config_helper.py
tabml/feature_manager.py
tabml/inference.py
tabml/metrics.py
tabml/model_analysis.py
tabml/model_wrappers.py
tabml/pipelines.py
tabml.egg-info/PKG-INFO
tabml.egg-info/SOURCES.txt
tabml.egg-info/dependency_links.txt
tabml.egg-info/requires.txt
tabml.egg-info/top_level.txt
tabml/examples/__init__.py
tabml/examples/housing/__init__.py
tabml/examples/housing/feature_manager.py
tabml/examples/housing/model_wrappers.py
tabml/examples/housing/pipelines.py
tabml/examples/housing/test_housing.py
tabml/examples/titanic/__init__.py
tabml/examples/titanic/feature_manager.py
tabml/examples/titanic/pipelines.py
tabml/examples/titanic/test_titanic.py
tabml/schemas/__init__.py
tabml/schemas/bundles.py
tabml/schemas/feature_config.py
tabml/schemas/pipeline_config.py
tabml/tests/__init__.py
tabml/tests/test_data_loaders.py
tabml/tests/test_data_processing.py
tabml/tests/test_experiment_manager.py
tabml/tests/test_feature_config_helper.py
tabml/tests/test_feature_manager.py
tabml/tests/test_metrics.py
tabml/utils/__init__.py
tabml/utils/embedding.py
tabml/utils/factory.py
tabml/utils/git.py
tabml/utils/logger.py
tabml/utils/utils.py