Metadata-Version: 2.1
Name: tabml
Version: 0.2.4
Summary: A package for machine learning with tabular data
Home-page: https://github.com/tiepvupsu/tabml
Author: Tiep Vu
Author-email: vuhuutiep@gmail.com
License: apache-2.0
Download-URL: https://github.com/tiepvupsu/tabml/archive/refs/tags/v0_1_17.tar.gz
Keywords: Machine Learning,Tabular
Platform: UNKNOWN
Classifier: Development Status :: 3 - Alpha
Classifier: Intended Audience :: Developers
Classifier: Topic :: Software Development :: Build Tools
Classifier: License :: OSI Approved :: Apache Software License
Classifier: Programming Language :: Python :: 3.8
